oocli/__init__.py
oocli/cli.py
oocli/clitools.py
oocli/config.py
oocli/data.py
oocli/datastores.py
oocli/libcloudfixes.py
oocli/projects.py
oocli/runs.py
oocli/services.py
oocli/tags.py
o_o-0.6.1.dist-info/licenses/LICENSE
o_o-0.6.1.dist-info/WHEEL
o_o-0.6.1.dist-info/entry_points.txt
o_o-0.6.1.dist-info/METADATA
o_o-0.6.1.dist-info/RECORD
