Metadata-Version: 2.4
Name: o-o
Version: 0.6.1
Summary: A command line interface for running cloud jobs
Author: Paul Novotny
Author-email: Paul Novotny <mail@paulnovo.us>
License-Expression: GPL-3.0-or-later
License-File: LICENSE
Classifier: Programming Language :: Python :: 3
Classifier: Operating System :: OS Independent
Requires-Dist: apache-libcloud==3.8.0
Requires-Dist: asciidag>=0.2.0
Requires-Dist: click>=8.2.1
Requires-Dist: gitpython>=3.1.44
Requires-Dist: paramiko>=3.5.1,<3.6
Requires-Dist: pendulum>=3.1.0
Requires-Dist: pydantic>=2.11.7
Requires-Dist: pydantic-extra-types>=2.10.5
Requires-Dist: pydantic-settings>=2.10.1
Requires-Dist: python-dotenv>=1.1.1
Requires-Dist: pyyaml>=6.0.2
Requires-Dist: requests>=2.32.4
Requires-Dist: typer>=0.16.0
Requires-Python: >=3.11
Project-URL: Homepage, https://o-o.tools
Project-URL: Issues, https://todo.sr.ht/~ootools/oocli
Project-URL: Source, https://git.sr.ht/~ootools/oocli
